[{"Year":1959,"Type":"Flood","Subtype":null,"Country":"China","Location":"North","Latitude":null,"Longitude":null,"Country Latitude":35.000074,"Country Longitude":104.999927,"Location Latitude":31.855753,"Location Longitude":117.2473491,"Smart Coords":null,"Start Year":1959,"Start Month":7.0,"Start Day":null,"End Year":1961,"End Month":7.0,"End Day":null,"Total Affected":null,"Total Deaths":2000000.0},{"Year":1959,"Type":"Storm","Subtype":null,"Country":"Brazil","Location":null,"Latitude":null,"Longitude":null,"Country Latitude":-10.3333333,"Country Longitude":-53.2,"Location Latitude":null,"Location Longitude":null,"Smart Coords":null,"Start Year":1959,"Start Month":8.0,"Start Day":null,"End Year":1959,"End Month":8.0,"End Day":null,"Total Affected":null,"Total Deaths":59.0},{"Year":1959,"Type":"Flood","Subtype":null,"Country":"Brazil","Location":null,"Latitude":null,"Longitude":null,"Country Latitude":-10.3333333,"Country Longitude":-53.2,"Location Latitude":null,"Location Longitude":null,"Smart Coords":null,"Start Year":1959,"Start Month":9.0,"Start Day":null,"End Year":1959,"End Month":9.0,"End Day":null,"Total Affected":null,"Total Deaths":100.0},{"Year":1959,"Type":"Storm","Subtype":"Convective storm","Country":"Canada","Location":"Newfoundland","Latitude":null,"Longitude":null,"Country Latitude":61.0666922,"Country Longitude":-107.991707,"Location Latitude":49.12120935,"Location Longitude":-56.6403111408,"Smart Coords":null,"Start Year":1959,"Start Month":2.0,"Start Day":16.0,"End Year":1959,"End Month":2.0,"End Day":16.0,"Total Affected":null,"Total Deaths":6.0},{"Year":1959,"Type":"Storm","Subtype":"Tropical cyclone","Country":"China","Location":null,"Latitude":null,"Longitude":null,"Country Latitude":35.000074,"Country Longitude":104.999927,"Location Latitude":null,"Location Longitude":null,"Smart Coords":null,"Start Year":1959,"Start Month":8.0,"Start Day":null,"End Year":1959,"End Month":8.0,"End Day":null,"Total Affected":null,"Total Deaths":1064.0},{"Year":1959,"Type":"Storm","Subtype":"Tropical cyclone","Country":"China","Location":"Fukien province","Latitude":null,"Longitude":null,"Country Latitude":35.000074,"Country Longitude":104.999927,"Location Latitude":24.4461659,"Location Longitude":118.0666993,"Smart Coords":null,"Start Year":1959,"Start Month":8.0,"Start Day":20.0,"End Year":1959,"End Month":8.0,"End Day":20.0,"Total Affected":null,"Total Deaths":720.0},{"Year":1959,"Type":"Flood","Subtype":null,"Country":"China","Location":null,"Latitude":null,"Longitude":null,"Country Latitude":35.000074,"Country Longitude":104.999927,"Location Latitude":null,"Location Longitude":null,"Smart Coords":null,"Start Year":1959,"Start Month":6.0,"Start Day":null,"End Year":1959,"End Month":6.0,"End Day":null,"Total Affected":null,"Total Deaths":187.0},{"Year":1959,"Type":"Flood","Subtype":null,"Country":"Colombia","Location":null,"Latitude":null,"Longitude":null,"Country Latitude":4.099917,"Country Longitude":-72.9088133,"Location Latitude":null,"Location Longitude":null,"Smart Coords":null,"Start Year":1959,"Start Month":6.0,"Start Day":null,"End Year":1959,"End Month":6.0,"End Day":null,"Total Affected":null,"Total Deaths":184.0},{"Year":1959,"Type":"Storm","Subtype":null,"Country":"Hong Kong","Location":null,"Latitude":null,"Longitude":null,"Country Latitude":22.352957,"Country Longitude":113.962891,"Location Latitude":null,"Location Longitude":null,"Smart Coords":null,"Start Year":1959,"Start Month":6.0,"Start Day":null,"End Year":1959,"End Month":6.0,"End Day":null,"Total Affected":null,"Total Deaths":43.0},{"Year":1959,"Type":"Flood","Subtype":null,"Country":"Haiti","Location":null,"Latitude":null,"Longitude":null,"Country Latitude":19.1399952,"Country Longitude":-72.3570972,"Location Latitude":null,"Location Longitude":null,"Smart Coords":null,"Start Year":1959,"Start Month":4.0,"Start Day":null,"End Year":1959,"End Month":4.0,"End Day":null,"Total Affected":null,"Total Deaths":50.0},{"Year":1959,"Type":"Earthquake","Subtype":"Ground movement","Country":"United States","Location":"Hebgen Lake (Montana)","Latitude":"44.712","Longitude":"-111.215","Country Latitude":39.7837304,"Country Longitude":-100.445882,"Location Latitude":44.7242442,"Location Longitude":-111.2246673989,"Smart Coords":null,"Start Year":1959,"Start Month":8.0,"Start Day":17.0,"End Year":1959,"End Month":8.0,"End Day":17.0,"Total Affected":null,"Total Deaths":28.0},{"Year":1959,"Type":"Flood","Subtype":null,"Country":"India","Location":"Kutch","Latitude":null,"Longitude":null,"Country Latitude":22.3511148,"Country Longitude":78.6677428,"Location Latitude":22.6612804,"Location Longitude":69.7625581,"Smart Coords":"[{\"Lat\": 22.6612804, \"Lng\": 69.7625581}]","Start Year":1959,"Start Month":7.0,"Start Day":4.0,"End Year":1959,"End Month":7.0,"End Day":4.0,"Total Affected":13000.0,"Total Deaths":17.0},{"Year":1959,"Type":"Flood","Subtype":null,"Country":"India","Location":null,"Latitude":null,"Longitude":null,"Country Latitude":22.3511148,"Country Longitude":78.6677428,"Location Latitude":null,"Location Longitude":null,"Smart Coords":null,"Start Year":1959,"Start Month":7.0,"Start Day":null,"End Year":1959,"End Month":7.0,"End Day":null,"Total Affected":null,"Total Deaths":104.0},{"Year":1959,"Type":"Flood","Subtype":null,"Country":"India","Location":null,"Latitude":null,"Longitude":null,"Country Latitude":22.3511148,"Country Longitude":78.6677428,"Location Latitude":null,"Location Longitude":null,"Smart Coords":null,"Start Year":1959,"Start Month":9.0,"Start Day":null,"End Year":1959,"End Month":9.0,"End Day":null,"Total Affected":null,"Total Deaths":500.0},{"Year":1959,"Type":"Storm","Subtype":"Tropical cyclone","Country":"Japan","Location":"Entire nation","Latitude":null,"Longitude":null,"Country Latitude":36.5748441,"Country Longitude":139.2394179,"Location Latitude":null,"Location Longitude":null,"Smart Coords":null,"Start Year":1959,"Start Month":9.0,"Start Day":26.0,"End Year":1959,"End Month":9.0,"End Day":26.0,"Total Affected":1500000.0,"Total Deaths":5098.0},{"Year":1959,"Type":"Storm","Subtype":"Tropical cyclone","Country":"Japan","Location":null,"Latitude":null,"Longitude":null,"Country Latitude":36.5748441,"Country Longitude":139.2394179,"Location Latitude":null,"Location Longitude":null,"Smart Coords":null,"Start Year":1959,"Start Month":8.0,"Start Day":null,"End Year":1959,"End Month":8.0,"End Day":null,"Total Affected":null,"Total Deaths":139.0},{"Year":1959,"Type":"Storm","Subtype":"Tropical cyclone","Country":"Japan","Location":null,"Latitude":null,"Longitude":null,"Country Latitude":36.5748441,"Country Longitude":139.2394179,"Location Latitude":null,"Location Longitude":null,"Smart Coords":null,"Start Year":1959,"Start Month":10.0,"Start Day":null,"End Year":1959,"End Month":10.0,"End Day":null,"Total Affected":null,"Total Deaths":27.0},{"Year":1959,"Type":"Flood","Subtype":null,"Country":"Japan","Location":null,"Latitude":null,"Longitude":null,"Country Latitude":36.5748441,"Country Longitude":139.2394179,"Location Latitude":null,"Location Longitude":null,"Smart Coords":null,"Start Year":1959,"Start Month":7.0,"Start Day":null,"End Year":1959,"End Month":7.0,"End Day":null,"Total Affected":null,"Total Deaths":41.0},{"Year":1959,"Type":"Storm","Subtype":"Tropical cyclone","Country":"Korea, Republic of","Location":null,"Latitude":null,"Longitude":null,"Country Latitude":36.638392,"Country Longitude":127.6961188,"Location Latitude":null,"Location Longitude":null,"Smart Coords":null,"Start Year":1959,"Start Month":9.0,"Start Day":17.0,"End Year":1959,"End Month":9.0,"End Day":17.0,"Total Affected":null,"Total Deaths":432.0},{"Year":1959,"Type":"Flood","Subtype":null,"Country":"Korea, Republic of","Location":null,"Latitude":null,"Longitude":null,"Country Latitude":36.638392,"Country Longitude":127.6961188,"Location Latitude":null,"Location Longitude":null,"Smart Coords":null,"Start Year":1959,"Start Month":7.0,"Start Day":null,"End Year":1959,"End Month":7.0,"End Day":null,"Total Affected":null,"Total Deaths":62.0},{"Year":1959,"Type":"Earthquake","Subtype":"Ground movement","Country":"Mexico","Location":"Gulf of Campeche (Vera Cruz state)","Latitude":"18.22","Longitude":"-94.416","Country Latitude":23.6585116,"Country Longitude":-102.0077097,"Location Latitude":null,"Location Longitude":null,"Smart Coords":null,"Start Year":1959,"Start Month":8.0,"Start Day":26.0,"End Year":1959,"End Month":8.0,"End Day":26.0,"Total Affected":200.0,"Total Deaths":25.0},{"Year":1959,"Type":"Storm","Subtype":"Tropical cyclone","Country":"Mexico","Location":"Jalisco & Colima","Latitude":null,"Longitude":null,"Country Latitude":23.6585116,"Country Longitude":-102.0077097,"Location Latitude":21.3745519,"Location Longitude":-101.9271426,"Smart Coords":null,"Start Year":1959,"Start Month":10.0,"Start Day":27.0,"End Year":1959,"End Month":10.0,"End Day":27.0,"Total Affected":null,"Total Deaths":960.0},{"Year":1959,"Type":"Flood","Subtype":null,"Country":"Mexico","Location":"West","Latitude":null,"Longitude":null,"Country Latitude":23.6585116,"Country Longitude":-102.0077097,"Location Latitude":null,"Location Longitude":null,"Smart Coords":null,"Start Year":1959,"Start Month":null,"Start Day":null,"End Year":1959,"End Month":null,"End Day":null,"Total Affected":null,"Total Deaths":2000.0},{"Year":1959,"Type":"Storm","Subtype":"Tropical cyclone","Country":"New Caledonia","Location":"Southern New Caledonia","Latitude":null,"Longitude":null,"Country Latitude":-21.3019905,"Country Longitude":165.4880773,"Location Latitude":null,"Location Longitude":null,"Smart Coords":null,"Start Year":1959,"Start Month":1.0,"Start Day":18.0,"End Year":1959,"End Month":1.0,"End Day":18.0,"Total Affected":null,"Total Deaths":1.0},{"Year":1959,"Type":"Storm","Subtype":"Tropical cyclone","Country":"Niue","Location":null,"Latitude":null,"Longitude":null,"Country Latitude":-19.0536414,"Country Longitude":-169.861341,"Location Latitude":null,"Location Longitude":null,"Smart Coords":null,"Start Year":1959,"Start Month":2.0,"Start Day":26.0,"End Year":1959,"End Month":2.0,"End Day":26.0,"Total Affected":1600.0,"Total Deaths":null},{"Year":1959,"Type":"Landslide","Subtype":"Avalanche","Country":"Pakistan","Location":"Lowarai Pass","Latitude":null,"Longitude":null,"Country Latitude":30.3308401,"Country Longitude":71.247499,"Location Latitude":null,"Location Longitude":null,"Smart Coords":null,"Start Year":1959,"Start Month":12.0,"Start Day":16.0,"End Year":1959,"End Month":12.0,"End Day":16.0,"Total Affected":null,"Total Deaths":48.0},{"Year":1959,"Type":"Flood","Subtype":null,"Country":"Pakistan","Location":null,"Latitude":null,"Longitude":null,"Country Latitude":30.3308401,"Country Longitude":71.247499,"Location Latitude":null,"Location Longitude":null,"Smart Coords":null,"Start Year":1959,"Start Month":7.0,"Start Day":null,"End Year":1959,"End Month":7.0,"End Day":null,"Total Affected":null,"Total Deaths":100.0},{"Year":1959,"Type":"Storm","Subtype":"Tropical cyclone","Country":"Philippines","Location":null,"Latitude":null,"Longitude":null,"Country Latitude":12.7503486,"Country Longitude":122.7312101,"Location Latitude":null,"Location Longitude":null,"Smart Coords":null,"Start Year":1959,"Start Month":12.0,"Start Day":null,"End Year":1959,"End Month":12.0,"End Day":null,"Total Affected":null,"Total Deaths":29.0},{"Year":1959,"Type":"Storm","Subtype":"Tropical cyclone","Country":"Taiwan","Location":null,"Latitude":null,"Longitude":null,"Country Latitude":23.9739374,"Country Longitude":120.9820179,"Location Latitude":null,"Location Longitude":null,"Smart Coords":null,"Start Year":1959,"Start Month":8.0,"Start Day":null,"End Year":1959,"End Month":8.0,"End Day":null,"Total Affected":null,"Total Deaths":1046.0},{"Year":1959,"Type":"Storm","Subtype":null,"Country":"United States","Location":null,"Latitude":null,"Longitude":null,"Country Latitude":39.7837304,"Country Longitude":-100.445882,"Location Latitude":null,"Location Longitude":null,"Smart Coords":null,"Start Year":1959,"Start Month":1.0,"Start Day":null,"End Year":1959,"End Month":1.0,"End Day":null,"Total Affected":null,"Total Deaths":71.0},{"Year":1959,"Type":"Storm","Subtype":"Tropical cyclone","Country":"Vanuatu","Location":"Southern Islands","Latitude":null,"Longitude":null,"Country Latitude":-16.5255069,"Country Longitude":168.1069154,"Location Latitude":null,"Location Longitude":null,"Smart Coords":null,"Start Year":1959,"Start Month":12.0,"Start Day":28.0,"End Year":1959,"End Month":12.0,"End Day":28.0,"Total Affected":null,"Total Deaths":null},{"Year":1959,"Type":"Flood","Subtype":null,"Country":"South Africa","Location":null,"Latitude":null,"Longitude":null,"Country Latitude":-28.8166236,"Country Longitude":24.991639,"Location Latitude":null,"Location Longitude":null,"Smart Coords":null,"Start Year":1959,"Start Month":5.0,"Start Day":null,"End Year":1959,"End Month":5.0,"End Day":null,"Total Affected":null,"Total Deaths":51.0},{"Year":1959,"Type":"Earthquake","Subtype":"Ground movement","Country":"Taiwan","Location":null,"Latitude":"22.078","Longitude":"121.105","Country Latitude":23.9739374,"Country Longitude":120.9820179,"Location Latitude":null,"Location Longitude":null,"Smart Coords":null,"Start Year":1959,"Start Month":8.0,"Start Day":15.0,"End Year":1959,"End Month":8.0,"End Day":15.0,"Total Affected":63.0,"Total Deaths":16.0}]